iwl/__init__.py
iwl/_parse.py
iwl/_tools.py
iwl/core.py
iwl/exceptions.py
iwl/parse.py
iwl/tools.py
iwl-0.0.1.dist-info/LICENSE
iwl-0.0.1.dist-info/METADATA
iwl-0.0.1.dist-info/WHEEL
iwl-0.0.1.dist-info/top_level.txt
iwl-0.0.1.dist-info/RECORD
